hydro_roll_core-0.0.3.dist-info/METADATA
hydro_roll_core-0.0.3.dist-info/WHEEL
hydro_roll_core-0.0.3.dist-info/entry_points.txt
hydro_roll_core-0.0.3.dist-info/license_files/LICENSE
hrc/event.py
hrc/LibCore.pyi
hrc/config.py
hrc/LibCore.py
hrc/log.py
hrc/feat/__init__.py
hrc/__init__.py
hrc/core.py
hrc/rule/__init__.py
hrc/rule/BaseRule/__init__.py
hrc/rule/BaseRule/CustomRule.py
hrc/rule/BaseRule/CharacterCard.py
hrc/rule/BaseRule/Wiki.py
hrc/cli.py
hrc/utils.py
hrc/py.typed
hrc/exceptions.py
hrc/dev/__init__.py
hrc/dev/character.py
hrc/doc/__init__.py
hrc/typing.py
hrc/perf/__init__.py
hrc/const.py
hrc/dependencies.py
hrc/LibCore.abi3.so
hydro_roll_core-0.0.3.dist-info/RECORD
