Metadata-Version: 2.3
Name: hydro-roll-core
Version: 0.0.3
Requires-Dist: pdfquery >=0.4.3
Requires-Dist: pydantic >=2.7.4
Requires-Dist: loguru >=0.7.2
License-File: LICENSE
Summary: Core of HydroRoll SDK.
Home-Page: https://core.hydroroll.team/
Author: HsiangNianian <i@jyunko.cn>
Author-email: 简律纯 <leader@hydroroll.team>
License:  AGPL-3.0
Requires-Python: >=3.9
Project-URL: homepage, https://core.hydroroll.team/
Project-URL: repository, https://github.com/HydroRoll-Team/HydroRollCore
Project-URL: documentation, https://core.hydroroll.team/
